equipy/__init__.py
equipy/fairness/__init__.py
equipy/fairness/_base.py
equipy/fairness/_wasserstein.py
equipy/graphs/__init__.py
equipy/graphs/_arrow_plot.py
equipy/graphs/_density_plot.py
equipy/graphs/_waterfall_plot.py
equipy/metrics/__init__.py
equipy/metrics/_fairness_metrics.py
equipy/metrics/_performance_metrics.py
equipy/utils/__init__.py
equipy/utils/checkers.py
equipy/utils/permutations/__init__.py
equipy/utils/permutations/_compute_permutations.py
equipy/utils/permutations/metrics/__init__.py
equipy/utils/permutations/metrics/_fairness_permutations.py
equipy/utils/permutations/metrics/_performance_permutations.py
equipy-0.0.11a0.dev0.dist-info/LICENSE
equipy-0.0.11a0.dev0.dist-info/METADATA
equipy-0.0.11a0.dev0.dist-info/WHEEL
equipy-0.0.11a0.dev0.dist-info/top_level.txt
equipy-0.0.11a0.dev0.dist-info/RECORD
