Metadata-Version: 2.1
Name: equipy
Version: 0.0.11a0.dev0
Summary: Equipy is a tool for fast, online fairness calibration
Home-page: UNKNOWN
Author: Agathe F, Suzie G, Francois H, Philipp R, Arthur C
Author-email: nocontact@email.com
License: UNKNOWN
Keywords: fairness,wasserstein
Platform: UNKNOWN
Classifier: Development Status :: 2 - Pre-Alpha
Classifier: License :: OSI Approved :: BSD License
Classifier: Programming Language :: Python :: 3
Classifier: Operating System :: OS Independent
License-File: LICENSE
Requires-Dist: numpy
Requires-Dist: scipy
Requires-Dist: scikit-learn
Requires-Dist: matplotlib
Requires-Dist: pandas
Requires-Dist: statsmodels
Requires-Dist: seaborn
